Metadata-Version: 2.4
Name: avrotize
Version: 3.0.2
Summary: Tools to convert from and to Avro Schema from various other schema languages.
Author-email: Clemens Vasters <clemensv@microsoft.com>
Requires-Python: >=3.10
Classifier: Programming Language :: Python :: 3
Classifier: License :: OSI Approved :: MIT License
Classifier: Operating System :: OS Independent
License-File: LICENSE
Requires-Dist: jsonschema>=4.23.0
Requires-Dist: lark>=1.1.9
Requires-Dist: pyarrow>=22.0.0
Requires-Dist: asn1tools>=0.167.0
Requires-Dist: jsonpointer>=3.0.0
Requires-Dist: jsonpath-ng>=1.6.1
Requires-Dist: jsoncomparison>=1.1.0
Requires-Dist: requests>=2.32.3
Requires-Dist: azure-kusto-data>=5.0.5
Requires-Dist: azure-identity>=1.17.1
Requires-Dist: datapackage>=1.15.4
Requires-Dist: jinja2>=3.1.4
Requires-Dist: pyiceberg>=0.10.0
Requires-Dist: pandas>=2.2.2
Requires-Dist: docker>=7.1.0
Requires-Dist: cddlparser>=0.5.0
Requires-Dist: json-structure>=0.1.8
Requires-Dist: pytest>=8.3.2 ; extra == "dev"
Requires-Dist: fastavro>=1.9.5 ; extra == "dev"
Requires-Dist: xmlschema>=3.3.2 ; extra == "dev"
Requires-Dist: xmlunittest>=1.0.1 ; extra == "dev"
Requires-Dist: pylint>=3.2.6 ; extra == "dev"
Requires-Dist: dataclasses_json>=0.6.7 ; extra == "dev"
Requires-Dist: dataclasses>=0.8 ; extra == "dev"
Requires-Dist: pydantic>=2.8.2 ; extra == "dev"
Requires-Dist: avro>=1.12.0 ; extra == "dev"
Requires-Dist: testcontainers>=4.7.2 ; extra == "dev"
Requires-Dist: pymysql>=1.1.1 ; extra == "dev"
Requires-Dist: psycopg2>=2.9.9 ; extra == "dev"
Requires-Dist: pyodbc>=5.1.0 ; extra == "dev"
Requires-Dist: pymongo>=4.8.0 ; extra == "dev"
Requires-Dist: oracledb>=2.3.0 ; extra == "dev"
Requires-Dist: cassandra-driver>=3.29.1 ; extra == "dev"
Requires-Dist: sqlalchemy>=2.0.32 ; extra == "dev"
Requires-Dist: graphql-core>=3.2.0 ; extra == "dev"
Provides-Extra: dev
